pipelines/__init__.py
pipelines/automated_tests.py
pipelines/base.py
pipelines/precommit.py
pipelines/prhandler.py
pipelines/publish.py
tests/__init__.py
tests/conftest.py
tests/test_cli.py
tests/test_config.py
tests/test_info.py
tests/test_providers.py
tests/test_repository.py
thipstercli/__init__.py
thipstercli/__main__.py
thipstercli/cli.py
thipstercli/config.py
thipstercli/constants.py
thipstercli/display.py
thipstercli/helpers.py
thipstercli/commands/__init__.py
thipstercli/commands/config.py
thipstercli/commands/info.py
thipstercli/commands/providers.py
thipstercli/commands/repository.py
thipstercli-0.6.8.dist-info/LICENSE
thipstercli-0.6.8.dist-info/METADATA
thipstercli-0.6.8.dist-info/WHEEL
thipstercli-0.6.8.dist-info/entry_points.txt
thipstercli-0.6.8.dist-info/top_level.txt
thipstercli-0.6.8.dist-info/RECORD
