Metadata-Version: 2.1
Name: thipstercli
Version: 0.6.8
Summary: CLI interface build with typer, designed to use the thipster package
Home-page: https://github.com/THipster/THipster-cli
Download-URL: https://github.com/THipster/THipster-cli.git
License: MIT
Keywords: thipster,cli,generator,infrastructure as code,iac,terraform,typer
Classifier: Development Status :: 1 - Planning
Classifier: Environment :: Console
Classifier: Programming Language :: Python :: 3.11
Classifier: License :: OSI Approved :: MIT License
Classifier: Operating System :: OS Independent
License-File: LICENSE
Requires-Dist: cdktf-cdktf-provider-google ==8.0.8
Requires-Dist: GitPython ==3.1.40
Requires-Dist: google-auth ==2.22.0
Requires-Dist: importlib-metadata ==6.8.0
Requires-Dist: importlib-resources ==6.1.1
Requires-Dist: thipster ==0.23.6
Requires-Dist: typer[all] ==0.9.0
Requires-Dist: validators ==0.22.0
